<?xml version="1.0"?>
<!DOCTYPE hibernate-mapping PUBLIC "-//Hibernate/Hibernate Mapping DTD 3.0//EN"
	"http://www.hibernate.org/dtd/hibernate-mapping-3.0.dtd">
<hibernate-mapping>
	<class name="com.gewara.model.bbs.DiaryBase">
		<id name="id" type="long" column="RECORDID">
			<generator class="sequence">
				<param name="sequence">diary_sequence</param>
			</generator>
		</id>
		<property name="tag" type="string" column="TAG"/>
		<property name="relatedid" type="long" column="RELATEDID" />
		<property name="category" type="string" column="CATEGORY"/>
		<property name="categoryid" type="long" column="CATEGORYID"/>
		
		<property name="subject" type="string" column="SUBJECT"/>
		<property name="addtime" type="timestamp" column="ADDTIME"/>
		<property name="updatetime" type="timestamp" column="UPDATETIME"/>
		<property name="replytime" type="timestamp" column="REPLYTIME"/>
		<property name="replycount" type="integer" column="REPLYCOUNT"/>
		<property name="clickedtimes" type="integer" column="VISITNUM"/>
	 	
		<property name="overdate" type="date" column="OVERDATE"/>
	 	<property name="utime" type="timestamp" column="SORTTIME"/>
	 	
		<property name="type" type="string" column="TYPE"/>
		<property name="flowernum" type="integer" column="FLOWERNUM"/>
		<property name="poohnum" type="integer" column="POOHNUM"/>
		<property name="sumnum" type="integer" formula="FLOWERNUM-POOHNUM"/>
		<property name="sumnumed" type="integer" formula="FLOWERNUM+POOHNUM"/>
		<property name="summary" type="string" column="SUMMARY"/>
		<property name="viewed" type="boolean" column="CHECKED"/>
	  
		<property name="status" type="string" column="STATUS"/>
		<property name="flag" type="string" column="FLAG"/>
		<property name="range" type="string" column="RANGE"/>
		
		<property name="communityid" type="long" column="COMMUID"/>
		<property name="memberid" type="long" column="MEMBERID"/>
		<property name="replyid"  type="long" column="REPLYMEMBERID"/>
		<property name="membername"  type="string" column="MEMBERNAME"/>
		<property name="replyname"  type="string" column="REPLYNAME"/>
		<property name="countycode" type="string" column="COUNTYCODE"/>
		<property name="moderatorid" type="long" column="MODERATORID" />
		<property name="citycode" type="string" column="CITYCODE" />
		<property name="division" type="string" column="DIVISION" />
		<property name="otherinfo" type="string" column="OTHERINFO" />
		<property name="diaryImage" type="string" column="DIARYIMAGE" />
		<!-- 2012 0808 -->
		<property name="ip" type="string" column="IP" />
		<union-subclass name="com.gewara.model.bbs.Diary"  table="DIARY"  dynamic-update="true" dynamic-insert="true" lazy="false"/>
		<union-subclass name="com.gewara.model.bbs.DiaryHist" table="DIARY_HIST" lazy="false" />
	</class>
</hibernate-mapping>
